luxtronik/__init__.py
luxtronik/calculations.py
luxtronik/datatypes.py
luxtronik/parameters.py
luxtronik/visibilities.py
luxtronik-0.3.14.dist-info/LICENCE.md
luxtronik-0.3.14.dist-info/METADATA
luxtronik-0.3.14.dist-info/WHEEL
luxtronik-0.3.14.dist-info/top_level.txt
luxtronik-0.3.14.dist-info/RECORD
