Metadata-Version: 2.1
Name: luxtronik
Version: 0.3.14
Summary: A luxtronik heatpump controller interface
Home-page: https://github.com/bouni/python-luxtronik
Author: Bouni
Author-email: bouni@owee.de
Classifier: Programming Language :: Python :: 3
Classifier: License :: OSI Approved :: MIT License
Classifier: Operating System :: OS Independent
License-File: LICENCE.md
